{
  "parent": "dragonsurvival:place_altar",
  "criteria": {
    "be_wing_kirin": {
      "conditions": {
        "player": [
          {
            "condition": "minecraft:entity_properties",
            "entity": "this",
            "predicate": {
              "type_specific": {
                "type": "dragonsurvival:dragon_predicate",
                "dragon_species": "dragonsurvival:wing_kirin"
              }
            }
          }
        ]
      },
      "trigger": "dragonsurvival:be_dragon"
    }
  },
  "display": {
    "description": {
      "translate": "dragonsurvival.advancement.wing_kirin/be_wing_kirin.desc"
    },
    "icon": {
      "count": 1,
      "id": "wing_kirin:wing_kirin_icon"
    },
    "title": {
      "translate": "dragonsurvival.advancement.wing_kirin/be_wing_kirin"
    }
  },
  "requirements": [
    [
      "be_wing_kirin"
    ]
  ],
  "rewards": {
    "experience": 12
  },
  "sends_telemetry_event": true
}